odoo9_addon_pos_restricted_customer_list-9.0.1.0.0.99.dev5-py3.8-nspkg.pth
odoo_addons/pos_restricted_customer_list/README.rst
odoo_addons/pos_restricted_customer_list/__init__.py
odoo_addons/pos_restricted_customer_list/__openerp__.py
odoo_addons/pos_restricted_customer_list/i18n/am.po
odoo_addons/pos_restricted_customer_list/i18n/ar.po
odoo_addons/pos_restricted_customer_list/i18n/bg.po
odoo_addons/pos_restricted_customer_list/i18n/bs.po
odoo_addons/pos_restricted_customer_list/i18n/ca.po
odoo_addons/pos_restricted_customer_list/i18n/cs.po
odoo_addons/pos_restricted_customer_list/i18n/da.po
odoo_addons/pos_restricted_customer_list/i18n/de.po
odoo_addons/pos_restricted_customer_list/i18n/el_GR.po
odoo_addons/pos_restricted_customer_list/i18n/en_GB.po
odoo_addons/pos_restricted_customer_list/i18n/es.po
odoo_addons/pos_restricted_customer_list/i18n/es_CR.po
odoo_addons/pos_restricted_customer_list/i18n/es_EC.po
odoo_addons/pos_restricted_customer_list/i18n/es_MX.po
odoo_addons/pos_restricted_customer_list/i18n/es_VE.po
odoo_addons/pos_restricted_customer_list/i18n/et.po
odoo_addons/pos_restricted_customer_list/i18n/eu.po
odoo_addons/pos_restricted_customer_list/i18n/fi.po
odoo_addons/pos_restricted_customer_list/i18n/fr.po
odoo_addons/pos_restricted_customer_list/i18n/fr_CA.po
odoo_addons/pos_restricted_customer_list/i18n/fr_CH.po
odoo_addons/pos_restricted_customer_list/i18n/gl.po
odoo_addons/pos_restricted_customer_list/i18n/hr.po
odoo_addons/pos_restricted_customer_list/i18n/hr_HR.po
odoo_addons/pos_restricted_customer_list/i18n/hu.po
odoo_addons/pos_restricted_customer_list/i18n/id.po
odoo_addons/pos_restricted_customer_list/i18n/it.po
odoo_addons/pos_restricted_customer_list/i18n/ja.po
odoo_addons/pos_restricted_customer_list/i18n/lt.po
odoo_addons/pos_restricted_customer_list/i18n/lv.po
odoo_addons/pos_restricted_customer_list/i18n/mk.po
odoo_addons/pos_restricted_customer_list/i18n/mn.po
odoo_addons/pos_restricted_customer_list/i18n/nb.po
odoo9_addon_pos_restricted_customer_list-9.0.1.0.0.99.dev5.dist-info/METADATA
odoo9_addon_pos_restricted_customer_list-9.0.1.0.0.99.dev5.dist-info/WHEEL
odoo9_addon_pos_restricted_customer_list-9.0.1.0.0.99.dev5.dist-info/namespace_packages.txt
odoo9_addon_pos_restricted_customer_list-9.0.1.0.0.99.dev5.dist-info/top_level.txt
odoo9_addon_pos_restricted_customer_list-9.0.1.0.0.99.dev5.dist-info/RECORD
