Metadata-Version: 2.1
Name: odoo9-addon-pos-restricted-customer-list
Version: 9.0.1.0.0.99.dev5
Summary: This module will limit the download of customer data to only those customers where this has been specifically requested.
Home-page: https://github.com/OCA/pos/tree/9.0/pos_restricted_customer_list
Author: Therp BV, Odoo Community Association (OCA)
Author-email: support@odoo-community.org
License: AGPL-3
Platform: UNKNOWN
Classifier: Programming Language :: Python
Classifier: Framework :: Odoo
Classifier: Framework :: Odoo :: 9.0
Classifier: License :: OSI Approved :: GNU Affero General Public License v3
Classifier: Development Status :: 5 - Production/Stable
Requires-Python: ~=2.7
Requires-Dist: odoo (<9.1a,>=9.0a)
